pydsef-0.2.0.dist-info/RECORD
pydsef-0.2.0.dist-info/WHEEL
pydsef-0.2.0.dist-info/top_level.txt
pydsef-0.2.0.dist-info/DESCRIPTION.rst
pydsef-0.2.0.dist-info/METADATA
pydsef-0.2.0.dist-info/metadata.json
pydsef/__init__.py
pydsef/service.py
pydsef/experiment.py
pydsef/util.py
