Metadata-Version: 2.0
Name: pydsef
Version: 0.2.0
Summary: A python library that provides convience functions for DSEF
Home-page: https://github.com/DSEF
Author: Samuel Thomas
Author-email: sgt43@cornell.edu
License: MIT
Platform: UNKNOWN
Requires-Python: >=3
Requires-Dist: rpyc
Requires-Dist: scp
Requires-Dist: pyyaml
